{
  "version": "v5.1",
  "updated_at": "2026-02-28",
  "indicators": {
    "equivalent_utilization_hours": {
      "id": "equivalent_utilization_hours",
      "name": "等效利用小时数",
      "description": "年利用小时数，发电量除以装机容量",
      "source": "constructed",
      "scope": "station",
      "level": "L2",
      "formula": "generation / installed_capacity",
      "inputs": ["generation", "installed_capacity"],
      "aggregation": "yearly",
      "unit": "h",
      "lifecycle_status": "approved",
      "owner": "system",
      "version": "1.0",
      "created_at": "2026-02-28",
      "computable": "✅",
      "data_source": "逆变器/人工",
      "priority": "竞赛核心指标"
    },
    "curtailment_rate": {
      "id": "curtailment_rate",
      "name": "弃光率",
      "description": "弃光电量占理论发电量的比例",
      "source": "constructed",
      "scope": "station",
      "level": "L2",
      "formula": "curtailment_energy / theoretical_generation * 100",
      "inputs": ["curtailment_energy", "theoretical_generation"],
      "aggregation": "daily",
      "unit": "%",
      "lifecycle_status": "approved",
      "owner": "system",
      "version": "1.0",
      "created_at": "2026-02-28",
      "computable": "⚠️",
      "data_source": "调度",
      "priority": "竞赛核心指标"
    },
    "plant_consumption_rate_comprehensive": {
      "id": "plant_consumption_rate_comprehensive",
      "name": "综合厂用电率",
      "description": "综合厂用电量占发电量的比例",
      "source": "constructed",
      "scope": "station",
      "level": "L2",
      "formula": "comprehensive_consumption / generation * 100",
      "inputs": ["comprehensive_consumption", "generation"],
      "aggregation": "daily",
      "unit": "%",
      "lifecycle_status": "approved",
      "owner": "system",
      "version": "1.0",
      "created_at": "2026-02-28",
      "computable": "⚠️",
      "data_source": "关口表",
      "priority": "竞赛核心指标"
    },
    "plant_overall_efficiency": {
      "id": "plant_overall_efficiency",
      "name": "光伏电站整体效率",
      "description": "实际发电量与理论发电量的比值",
      "source": "constructed",
      "scope": "station",
      "level": "L2",
      "formula": "actual_generation / theoretical_generation * 100",
      "inputs": ["actual_generation", "theoretical_generation"],
      "aggregation": "daily",
      "unit": "%",
      "lifecycle_status": "approved",
      "owner": "system",
      "version": "1.0",
      "created_at": "2026-02-28",
      "computable": "⚠️",
      "data_source": "逆变器/理论计算",
      "priority": "竞赛核心指标"
    },
    "generation_duration": {
      "id": "generation_duration",
      "name": "发电时长",
      "description": "设备处于发电状态的累计时长",
      "source": "constructed",
      "scope": "inverter",
      "level": "L1",
      "formula": "count(status == 'generating')",
      "inputs": ["status"],
      "aggregation": "daily",
      "unit": "h",
      "lifecycle_status": "approved",
      "owner": "system",
      "version": "1.0",
      "created_at": "2026-02-28",
      "computable": "✅",
      "data_source": "逆变器",
      "priority": "竞赛核心指标"
    }
  }
}